{
  "slug": "reupholstering-a-piano-stool",
  "title": "Reupholstering a piano stool",
  "subtitle": "Re-cover a drop-in padded seat with new fabric and fresh foam",
  "excerpt": "How to strip and re-cover the padded seat on a drop-in piano stool: removing the old cover, replacing tired foam, wrapping with dacron, cutting the new fabric, and stapling it for a tight finish.",
  "type": "PATTERN",
  "categorySlug": "home-repair",
  "subCategorySlug": "upholstery-and-leather",
  "difficulty": "BEGINNER",
  "season": null,
  "timeMinutes": null,
  "sourceType": "PUBLIC_DOMAIN",
  "sourceNotes": "Barnett, The Upholsterer's Step-by-Step Handbook.",
  "recipeTools": [
    { "slug": "staple-remover-upholstery", "isOptional": false },
    { "slug": "upholstery-shears", "isOptional": false },
    { "slug": "staple-gun-manual", "isOptional": false },
    { "slug": "t50-staples", "isOptional": false },
    { "slug": "upholstery-foam-sheets", "isOptional": false },
    { "slug": "dacron-wrap", "isOptional": false }
  ],
  "techniqueSlugs": [],
  "criticalTechniques": [],
  "aliases": [
    "piano stool seat recover",
    "drop-in seat re-cover",
    "stool seat upholstery"
  ],
  "glossaryTerms": [
    {
      "slug": "drop-in-pad",
      "term": "Drop-in pad",
      "definition": "A padded seat board that sits in a rebate in a chair or stool frame and lifts out without any fixings. The frame holds the pad by weight and rebate depth alone. Drop-in pads are the easiest upholstery work: the entire re-cover is done with the pad on the bench, away from the frame."
    }
  ],
  "body": {
    "type": "doc",
    "content": [
      {
        "type": "paragraph",
        "content": [
          { "type": "text", "text": "A piano stool " },
          { "type": "text", "marks": [{ "type": "glossaryTooltip", "attrs": { "termSlug": "drop-in-pad" } }], "text": "drop-in pad" },
          { "type": "text", "text": " is the most accessible upholstery project: the pad lifts out, all work is done on the bench, and the result is immediately visible. Replace the foam if it is flat or misshapen; worn foam will show through any new cover fabric." }
        ]
      },
      {
        "type": "heading",
        "attrs": { "level": 2 },
        "content": [{ "type": "text", "text": "Step 1, remove the old cover" }]
      },
      {
        "type": "paragraph",
        "content": [
          { "type": "text", "text": "Lift the pad from the stool. Turn it upside down and remove all staples and tacks with the staple remover, working around the perimeter. Pull the old cover fabric off the pad board. If the underside has a dust cover (black or white woven fabric), remove this too." }
        ]
      },
      {
        "type": "heading",
        "attrs": { "level": 2 },
        "content": [{ "type": "text", "text": "Step 2, replace the foam" }]
      },
      {
        "type": "paragraph",
        "content": [
          { "type": "text", "text": "Peel or cut off the old foam from the pad board. Cut a piece of CMHR foam to the exact size of the board top using the upholstery shears; CMHR foam cuts cleanly with sharp shears. A 50 mm medium-density foam is appropriate for a piano stool; 25 mm is too thin and will compress to nothing within a year. Secure the foam to the board with a thin smear of contact adhesive around the top edges only." }
        ]
      },
      {
        "type": "heading",
        "attrs": { "level": 2 },
        "content": [{ "type": "text", "text": "Step 3, wrap with dacron" }]
      },
      {
        "type": "paragraph",
        "content": [
          { "type": "text", "text": "Cut a piece of dacron wrap approximately 100 mm larger than the pad on all four sides. Lay it over the foam and smooth it over the pad edges without compressing the foam. Staple the dacron to the underside of the board at 100 mm intervals, keeping it taut but not distorting the foam shape. Trim the excess dacron to within 20 mm of the staple line." }
        ]
      },
      {
        "type": "heading",
        "attrs": { "level": 2 },
        "content": [{ "type": "text", "text": "Step 4, cut and apply the cover fabric" }]
      },
      {
        "type": "paragraph",
        "content": [
          { "type": "text", "text": "Cut the cover fabric with the upholstery shears to the pad board size plus 60 mm on all four sides. Lay the fabric face-down on the bench, place the pad foam-side-down in the centre, and pull the fabric over the first side. Place one staple at each midpoint of all four sides to anchor the fabric, then check the face for puckers and wrinkles before completing. Work outward from the centre on each side, pulling the fabric firm and stapling at 40 mm intervals. Cut mitred folds at each corner and staple them flat." }
        ]
      },
      {
        "type": "heading",
        "attrs": { "level": 2 },
        "content": [{ "type": "text", "text": "Troubleshooter" }]
      },
      {
        "type": "troubleshooter",
        "content": [
          {
            "type": "troubleshooterRow",
            "attrs": {
              "symptom": "Cover fabric puckers or creases across the top",
              "cause": "Fabric was pulled unevenly, or the first staple row on one side was tighter than the other.",
              "fix": "Remove all staples and start again from the midpoint anchors, pulling equal tension on opposite sides before stapling."
            }
          },
          {
            "type": "troubleshooterRow",
            "attrs": {
              "symptom": "Pad does not sit flat in the stool rebate after recovering",
              "cause": "The dacron or foam extends too far over the edge and is adding height on one side.",
              "fix": "Trim the dacron to the exact edge of the board and re-check. If the foam is oversized, trim it back 2 mm on the affected sides."
            }
          }
        ]
      }
    ]
  }
}
