{
  "slug": "e-spinner-for-beginners",
  "title": "Getting started with an e-spinner",
  "subtitle": "Setting up and using an electric spinning wheel for the first time",
  "excerpt": "An e-spinner (electric spinning wheel) uses a motor in place of a treadle to drive the flyer and bobbin. The advantages are consistent speed, portability, and low physical demand, useful for people with mobility limitations or for travel spinning. The technique is identical to treadle spinning; the adjustment is in controlling motor speed rather than treadle rhythm.",
  "type": "TECHNIQUE",
  "categorySlug": "fibre-arts",
  "subCategorySlug": "spinning",
  "difficulty": "BEGINNER",
  "season": null,
  "sourceType": "SYNTHESISED",
  "sourceNotes": "E-spinner technique is an established subject in contemporary spinning instruction. Observation-led.",
  "recipeTools": [
    { "slug": "spinning-wheel-e-spinner", "isOptional": false },
    { "slug": "niddy-noddy", "isOptional": false }
  ],
  "glossaryTerms": [
    {
      "slug": "e-spinner",
      "term": "E-spinner",
      "definition": "An electric spinning wheel in which a small motor drives the flyer assembly, replacing the treadle. Speed is controlled by a dial or footswitch rather than treadle cadence."
    },
    {
      "slug": "take-up",
      "term": "Take-up",
      "definition": "The tension that draws spun yarn onto the bobbin. On an e-spinner, take-up is set by adjusting the drive-band tension or the bobbin whorl size. Too much take-up pulls the yarn in before it is twisted; too little allows it to balloon."
    }
  ],
  "aliases": [
    "electric spinning wheel",
    "e-spinner tutorial",
    "electric wheel spinning"
  ],
  "techniqueSlugs": ["spinning-a-dk-yarn-on-the-wheel", "the-short-forward-draw"],
  "criticalTechniques": [],
  "body": {
    "type": "doc",
    "content": [
      {
        "type": "paragraph",
        "content": [
          {
            "type": "text",
            "text": "An "
          },
          {
            "type": "text",
            "marks": [{ "type": "glossaryTooltip", "attrs": { "termSlug": "e-spinner" } }],
            "text": "e-spinner"
          },
          {
            "type": "text",
            "text": " runs identically to a treadle wheel in every respect except that the motor replaces foot power. The flyer, orifice, bobbin, and drive band work the same way. The main operational adjustment is learning to control "
          },
          {
            "type": "text",
            "marks": [{ "type": "glossaryTooltip", "attrs": { "termSlug": "take-up" } }],
            "text": "take-up"
          },
          {
            "type": "text",
            "text": " by dial rather than by treadle pressure."
          }
        ]
      },
      {
        "type": "infoPanel",
        "attrs": {
          "tone": "warning",
          "title": "Wheel safety",
          "body": "Keep loose hair and clothing away from the flyer and drive band. Switch the motor off before changing bobbins or threading the orifice."
        }
      },
      {
        "type": "heading",
        "attrs": { "level": 2 },
        "content": [{ "type": "text", "text": "What you need" }]
      },
      {
        "type": "suppliesCard",
        "attrs": {
          "heading": "Materials and tools",
          "items": [
            { "name": "E-spinner with at least one bobbin", "qty": "1" },
            { "name": "Prepared roving or top for practice", "qty": "30 g" },
            { "name": "Niddy-noddy (for winding off)", "qty": "1" }
          ]
        }
      },
      {
        "type": "heading",
        "attrs": { "level": 2 },
        "content": [{ "type": "text", "text": "Method" }]
      },
      {
        "type": "heading",
        "attrs": { "level": 3 },
        "content": [{ "type": "text", "text": "Step 1: Thread the leader and set speed" }]
      },
      {
        "type": "paragraph",
        "content": [
          {
            "type": "text",
            "text": "Thread a leader (short length of scrap yarn) through the orifice and tie it to the bobbin. Set the motor speed to its lowest setting. Turn the motor on and check that the bobbin takes up the leader without pulling it too fast. Ideal take-up speed for DK: the leader feeds onto the bobbin at roughly the same pace as normal walking."
          }
        ]
      },
      {
        "type": "heading",
        "attrs": { "level": 3 },
        "content": [{ "type": "text", "text": "Step 2: Attach the fibre and begin drafting" }]
      },
      {
        "type": "paragraph",
        "content": [
          {
            "type": "text",
            "text": "Attach the roving to the leader. Begin drafting with whichever method suits the fibre preparation. The e-spinner's consistent speed helps maintain even twist insertion; the main learning is matching drafting speed to motor speed. Draft slower or faster until the twist entering the yarn looks even."
          }
        ]
      },
      {
        "type": "heading",
        "attrs": { "level": 3 },
        "content": [{ "type": "text", "text": "Step 3: Adjust speed for yarn weight" }]
      },
      {
        "type": "paragraph",
        "content": [
          {
            "type": "text",
            "text": "Faster motor speed inserts more twist per length of drafted fibre, useful for fine yarn and lace. Slower speed inserts less twist, appropriate for bulky yarn and woollen-draw work. On most e-spinners, the flyer ratios are also swappable (like interchangeable whorls on a treadle wheel); use a higher-ratio whorl for fine spinning, a lower ratio for bulky."
          }
        ]
      },
      {
        "type": "troubleshooter",
        "attrs": {
          "heading": "Common problems",
          "intro": "Two common problems on first use of an e-spinner.",
          "items": [
            {
              "symptom": "Yarn keeps breaking at the orifice",
              "cause": "Take-up tension too high: the bobbin is pulling the yarn in faster than it is being spun.",
              "fix": "Reduce take-up by loosening the drive-band tension or moving to a whorl with a lower ratio. The yarn should feed onto the bobbin without resistance from the spinner's hand."
            },
            {
              "symptom": "Motor stalls under bobbin weight",
              "cause": "Bobbin is overfull or the drive band has slipped.",
              "fix": "Check drive band tension and re-seat it. Wind the yarn off onto the niddy-noddy if the bobbin is above two-thirds full."
            }
          ]
        }
      }
    ]
  }
}
